trio_inspector/__init__.py
trio_inspector/_version.py
trio_inspector/inspector.py
trio_inspector/serialization.py
trio_inspector/static/index.html
trio_inspector/static/main.js
trio_inspector/static/style.css
trio_inspector-0.0.3.dist-info/LICENSE
trio_inspector-0.0.3.dist-info/LICENSE.APACHE2
trio_inspector-0.0.3.dist-info/LICENSE.MIT
trio_inspector-0.0.3.dist-info/METADATA
trio_inspector-0.0.3.dist-info/WHEEL
trio_inspector-0.0.3.dist-info/top_level.txt
trio_inspector-0.0.3.dist-info/RECORD
