Metadata-Version: 2.1
Name: trio-inspector
Version: 0.0.3
Summary: A browser-based monitor for Trio
Home-page: https://github.com/syncrypt/trio-inspector/
Author: Hannes Gräuler
Author-email: hannes@syncrypt.space
License: MIT -or- Apache License 2.0
Platform: UNKNOWN
Classifier: Development Status :: 3 - Alpha
Classifier: Framework :: Trio
Classifier: Intended Audience :: Developers
Classifier: License :: OSI Approved :: Apache Software License
Classifier: License :: OSI Approved :: MIT License
Classifier: Operating System :: MacOS :: MacOS X
Classifier: Operating System :: Microsoft :: Windows
Classifier: Operating System :: POSIX :: Linux
Classifier: Programming Language :: Python :: 3 :: Only
Classifier: Programming Language :: Python :: Implementation :: CPython
Classifier: Programming Language :: Python :: Implementation :: PyPy
Classifier: Topic :: Internet :: WWW/HTTP :: WSGI :: Application
Classifier: Topic :: Software Development :: Debuggers
Requires-Python: >=3.7
Requires-Dist: trio
Requires-Dist: trio-typing
Requires-Dist: hypercorn
Requires-Dist: quart-trio
Requires-Dist: quart
Requires-Dist: quart-cors
